[
  {
    "id": "ext_Punta-Leona_3061a04992c91bea",
    "type": "photo",
    "source_path": "/Volumes/ADATA SC740/Smugmug Backup/Galleries/Costa-Rica-Gallery/Punta-Leona/2021-06-11 09.12.03.jpg",
    "gallery_folder": "Costa-Rica-Gallery/Punta-Leona",
    "gallery_id": 80,
    "gallery_slug": "punta-leona",
    "filename": "2021-06-11 09.12.03.jpg",
    "content_hash": "3061a04992c91beac9a685c36f2f1eed839d9b081d081d9943e3c23467d86db1",
    "size": 5717567,
    "approved": true,
    "priority": 50,
    "attempt_count": 0,
    "status": "skipped",
    "skip_reason": "duplicate"
  },
  {
    "id": "ext_Punta-Leona_b608996063393250",
    "type": "photo",
    "source_path": "/Volumes/ADATA SC740/Smugmug Backup/Galleries/Costa-Rica-Gallery/Punta-Leona/2021-06-11 09.32.26.jpg",
    "gallery_folder": "Costa-Rica-Gallery/Punta-Leona",
    "gallery_id": 80,
    "gallery_slug": "punta-leona",
    "filename": "2021-06-11 09.32.26.jpg",
    "content_hash": "b6089960633932506421e6b8ef7c4a74a18a08a4211a6cd0aae6475a0a7e4f58",
    "size": 8754030,
    "approved": true,
    "priority": 50,
    "attempt_count": 0,
    "status": "skipped",
    "skip_reason": "duplicate"
  },
  {
    "id": "ext_Punta-Leona_eaf97aa40d0326d1",
    "type": "photo",
    "source_path": "/Volumes/ADATA SC740/Smugmug Backup/Galleries/Costa-Rica-Gallery/Punta-Leona/2021-06-11 09.36.42.jpg",
    "gallery_folder": "Costa-Rica-Gallery/Punta-Leona",
    "gallery_id": 80,
    "gallery_slug": "punta-leona",
    "filename": "2021-06-11 09.36.42.jpg",
    "content_hash": "eaf97aa40d0326d12130be06627709abeb1d46c36df307b0deb1119a4d89dbba",
    "size": 6645505,
    "approved": true,
    "priority": 50,
    "attempt_count": 0,
    "status": "skipped",
    "skip_reason": "duplicate"
  },
  {
    "id": "ext_Punta-Leona_6a6c8c2964c1ded4",
    "type": "photo",
    "source_path": "/Volumes/ADATA SC740/Smugmug Backup/Galleries/Costa-Rica-Gallery/Punta-Leona/2021-06-11 09.43.23.jpg",
    "gallery_folder": "Costa-Rica-Gallery/Punta-Leona",
    "gallery_id": 80,
    "gallery_slug": "punta-leona",
    "filename": "2021-06-11 09.43.23.jpg",
    "content_hash": "6a6c8c2964c1ded485cbf23060ed167ad6aa074315ea346473897cd16d40f3ae",
    "size": 3559030,
    "approved": true,
    "priority": 50,
    "attempt_count": 0,
    "status": "skipped",
    "skip_reason": "duplicate"
  },
  {
    "id": "ext_Punta-Leona_3af746832cb230af",
    "type": "photo",
    "source_path": "/Volumes/ADATA SC740/Smugmug Backup/Galleries/Costa-Rica-Gallery/Punta-Leona/2021-06-11 10.53.14.jpg",
    "gallery_folder": "Costa-Rica-Gallery/Punta-Leona",
    "gallery_id": 80,
    "gallery_slug": "punta-leona",
    "filename": "2021-06-11 10.53.14.jpg",
    "content_hash": "3af746832cb230afd143684a71714bdf0fcf91ba018d8e7e8dc4421b147bfa33",
    "size": 4989821,
    "approved": true,
    "priority": 50,
    "attempt_count": 0,
    "status": "skipped",
    "skip_reason": "duplicate"
  },
  {
    "id": "ext_Punta-Leona_fa6ca8e5a1451b89",
    "type": "photo",
    "source_path": "/Volumes/ADATA SC740/Smugmug Backup/Galleries/Costa-Rica-Gallery/Punta-Leona/2021-06-11 12.01.24.jpg",
    "gallery_folder": "Costa-Rica-Gallery/Punta-Leona",
    "gallery_id": 80,
    "gallery_slug": "punta-leona",
    "filename": "2021-06-11 12.01.24.jpg",
    "content_hash": "fa6ca8e5a1451b8985f6c9e0a2f9317aebe4ffe6c5ce9bfd35bffd206dcf7856",
    "size": 7865025,
    "approved": true,
    "priority": 50,
    "attempt_count": 0,
    "status": "skipped",
    "skip_reason": "duplicate"
  },
  {
    "id": "ext_Punta-Leona_072f98d9848653cd",
    "type": "photo",
    "source_path": "/Volumes/ADATA SC740/Smugmug Backup/Galleries/Costa-Rica-Gallery/Punta-Leona/2023-11-24 15.19.14.jpg",
    "gallery_folder": "Costa-Rica-Gallery/Punta-Leona",
    "gallery_id": 80,
    "gallery_slug": "punta-leona",
    "filename": "2023-11-24 15.19.14.jpg",
    "content_hash": "072f98d9848653cd57ce7e73c640110ab68fe78fc408c276185bc11ab63c6a05",
    "size": 3752379,
    "approved": true,
    "priority": 50,
    "attempt_count": 0,
    "status": "skipped",
    "skip_reason": "duplicate"
  },
  {
    "id": "ext_Punta-Leona_d95820f58587f98f",
    "type": "photo",
    "source_path": "/Volumes/ADATA SC740/Smugmug Backup/Galleries/Costa-Rica-Gallery/Punta-Leona/2023-11-24 16.24.57.jpg",
    "gallery_folder": "Costa-Rica-Gallery/Punta-Leona",
    "gallery_id": 80,
    "gallery_slug": "punta-leona",
    "filename": "2023-11-24 16.24.57.jpg",
    "content_hash": "d95820f58587f98f32a268d293cadff53b6e6ea6d84365875745b83e86525144",
    "size": 3166188,
    "approved": true,
    "priority": 50,
    "attempt_count": 0,
    "status": "skipped",
    "skip_reason": "duplicate"
  },
  {
    "id": "ext_Punta-Leona_5316e242df468a9c",
    "type": "photo",
    "source_path": "/Volumes/ADATA SC740/Smugmug Backup/Galleries/Costa-Rica-Gallery/Punta-Leona/2023-11-24 16.25.13.jpg",
    "gallery_folder": "Costa-Rica-Gallery/Punta-Leona",
    "gallery_id": 80,
    "gallery_slug": "punta-leona",
    "filename": "2023-11-24 16.25.13.jpg",
    "content_hash": "5316e242df468a9c0c9e221919fb2781bfc6fd5dcfce52bca163940f95bfbedd",
    "size": 2938638,
    "approved": true,
    "priority": 50,
    "attempt_count": 0,
    "status": "skipped",
    "skip_reason": "duplicate"
  },
  {
    "id": "ext_Punta-Leona_4a3c98a7f91db268",
    "type": "photo",
    "source_path": "/Volumes/ADATA SC740/Smugmug Backup/Galleries/Costa-Rica-Gallery/Punta-Leona/2023-11-24 17.31.46.jpg",
    "gallery_folder": "Costa-Rica-Gallery/Punta-Leona",
    "gallery_id": 80,
    "gallery_slug": "punta-leona",
    "filename": "2023-11-24 17.31.46.jpg",
    "content_hash": "4a3c98a7f91db268547bc8372c2f2844b95ea4bde9d93c159d2d1034d694c9a2",
    "size": 3731304,
    "approved": true,
    "priority": 50,
    "attempt_count": 0,
    "status": "skipped",
    "skip_reason": "duplicate"
  },
  {
    "id": "ext_Punta-Leona_7005576bc772d56e",
    "type": "photo",
    "source_path": "/Volumes/ADATA SC740/Smugmug Backup/Galleries/Costa-Rica-Gallery/Punta-Leona/2023-11-24 17.33.18.jpg",
    "gallery_folder": "Costa-Rica-Gallery/Punta-Leona",
    "gallery_id": 80,
    "gallery_slug": "punta-leona",
    "filename": "2023-11-24 17.33.18.jpg",
    "content_hash": "7005576bc772d56e3f2af0faa7f60ce31520080ce008562a505a662d3d5476f4",
    "size": 3476376,
    "approved": true,
    "priority": 50,
    "attempt_count": 0,
    "status": "skipped",
    "skip_reason": "duplicate"
  },
  {
    "id": "ext_Punta-Leona_1a9b49f4f4205026",
    "type": "photo",
    "source_path": "/Volumes/ADATA SC740/Smugmug Backup/Galleries/Costa-Rica-Gallery/Punta-Leona/2023-11-25 16.57.03.jpg",
    "gallery_folder": "Costa-Rica-Gallery/Punta-Leona",
    "gallery_id": 80,
    "gallery_slug": "punta-leona",
    "filename": "2023-11-25 16.57.03.jpg",
    "content_hash": "1a9b49f4f420502606e90497704cb5e13107a32168e7cf38b5e323108f768580",
    "size": 4736309,
    "approved": true,
    "priority": 50,
    "attempt_count": 0,
    "status": "skipped",
    "skip_reason": "duplicate"
  },
  {
    "id": "ext_Punta-Leona_c212e8521e32f0bc",
    "type": "photo",
    "source_path": "/Volumes/ADATA SC740/Smugmug Backup/Galleries/Costa-Rica-Gallery/Punta-Leona/2023-11-25 17.04.40.jpg",
    "gallery_folder": "Costa-Rica-Gallery/Punta-Leona",
    "gallery_id": 80,
    "gallery_slug": "punta-leona",
    "filename": "2023-11-25 17.04.40.jpg",
    "content_hash": "c212e8521e32f0bcb6de599c06cbb274cdcac4d644039506d0994680f2128bd5",
    "size": 4161982,
    "approved": true,
    "priority": 50,
    "attempt_count": 0,
    "status": "skipped",
    "skip_reason": "duplicate"
  },
  {
    "id": "ext_Punta-Leona_10975510871aad55",
    "type": "photo",
    "source_path": "/Volumes/ADATA SC740/Smugmug Backup/Galleries/Costa-Rica-Gallery/Punta-Leona/2023-11-25 17.04.42.jpg",
    "gallery_folder": "Costa-Rica-Gallery/Punta-Leona",
    "gallery_id": 80,
    "gallery_slug": "punta-leona",
    "filename": "2023-11-25 17.04.42.jpg",
    "content_hash": "10975510871aad55bf3181e0e0451671eb43e0fe73aaa74b5efbd3002414d650",
    "size": 3635148,
    "approved": true,
    "priority": 50,
    "attempt_count": 0,
    "status": "skipped",
    "skip_reason": "duplicate"
  },
  {
    "id": "ext_Punta-Leona_21f3effb268e10ad",
    "type": "photo",
    "source_path": "/Volumes/ADATA SC740/Smugmug Backup/Galleries/Costa-Rica-Gallery/Punta-Leona/2023-11-26 11.31.14.jpg",
    "gallery_folder": "Costa-Rica-Gallery/Punta-Leona",
    "gallery_id": 80,
    "gallery_slug": "punta-leona",
    "filename": "2023-11-26 11.31.14.jpg",
    "content_hash": "21f3effb268e10adb753dde77f5753a1d06974ce3522373b3720b9996515c471",
    "size": 6315102,
    "approved": true,
    "priority": 50,
    "attempt_count": 0,
    "status": "skipped",
    "skip_reason": "duplicate"
  },
  {
    "id": "ext_Punta-Leona_c13467695d6763bc",
    "type": "photo",
    "source_path": "/Volumes/ADATA SC740/Smugmug Backup/Galleries/Costa-Rica-Gallery/Punta-Leona/2023-11-26 11.31.15.jpg",
    "gallery_folder": "Costa-Rica-Gallery/Punta-Leona",
    "gallery_id": 80,
    "gallery_slug": "punta-leona",
    "filename": "2023-11-26 11.31.15.jpg",
    "content_hash": "c13467695d6763bc27d3d0589cb22837f0c7f0e8e0653bc467024c14f498c4f6",
    "size": 5998722,
    "approved": true,
    "priority": 50,
    "attempt_count": 0,
    "status": "skipped",
    "skip_reason": "duplicate"
  },
  {
    "id": "ext_Punta-Leona_04b199df11a1f97c",
    "type": "photo",
    "source_path": "/Volumes/ADATA SC740/Smugmug Backup/Galleries/Costa-Rica-Gallery/Punta-Leona/2023-11-26 11.34.13.jpg",
    "gallery_folder": "Costa-Rica-Gallery/Punta-Leona",
    "gallery_id": 80,
    "gallery_slug": "punta-leona",
    "filename": "2023-11-26 11.34.13.jpg",
    "content_hash": "04b199df11a1f97ce87b7a537d79d18a9fa101fab90023db9b5c09de5034855f",
    "size": 4022725,
    "approved": true,
    "priority": 50,
    "attempt_count": 0,
    "status": "skipped",
    "skip_reason": "duplicate"
  },
  {
    "id": "ext_Punta-Leona_663bcf02bed317be",
    "type": "photo",
    "source_path": "/Volumes/ADATA SC740/Smugmug Backup/Galleries/Costa-Rica-Gallery/Punta-Leona/2023-11-26 12.52.25.jpg",
    "gallery_folder": "Costa-Rica-Gallery/Punta-Leona",
    "gallery_id": 80,
    "gallery_slug": "punta-leona",
    "filename": "2023-11-26 12.52.25.jpg",
    "content_hash": "663bcf02bed317beef260af663efb62f520827f731a5f89726b0a009e6ed8f74",
    "size": 4420303,
    "approved": true,
    "priority": 50,
    "attempt_count": 0,
    "status": "skipped",
    "skip_reason": "duplicate"
  },
  {
    "id": "ext_Punta-Leona_161f46463993052f",
    "type": "photo",
    "source_path": "/Volumes/ADATA SC740/Smugmug Backup/Galleries/Costa-Rica-Gallery/Punta-Leona/2023-11-26 12.52.28.jpg",
    "gallery_folder": "Costa-Rica-Gallery/Punta-Leona",
    "gallery_id": 80,
    "gallery_slug": "punta-leona",
    "filename": "2023-11-26 12.52.28.jpg",
    "content_hash": "161f46463993052fc12e0e3d3cbf97bbe67a26267b981da8c4612c5e5f8f2e2b",
    "size": 4017790,
    "approved": true,
    "priority": 50,
    "attempt_count": 0,
    "status": "skipped",
    "skip_reason": "duplicate"
  },
  {
    "id": "ext_Punta-Leona_5028f02935f17fd4",
    "type": "photo",
    "source_path": "/Volumes/ADATA SC740/Smugmug Backup/Galleries/Costa-Rica-Gallery/Punta-Leona/2023-11-26 13.54.44.jpg",
    "gallery_folder": "Costa-Rica-Gallery/Punta-Leona",
    "gallery_id": 80,
    "gallery_slug": "punta-leona",
    "filename": "2023-11-26 13.54.44.jpg",
    "content_hash": "5028f02935f17fd413f7b263f4771ce66932be81b465891005ab3606f1503e50",
    "size": 6248547,
    "approved": true,
    "priority": 50,
    "attempt_count": 0,
    "status": "skipped",
    "skip_reason": "duplicate"
  },
  {
    "id": "ext_Isla-Tortuga_3d8ad57f8cc97819",
    "type": "photo",
    "source_path": "/Volumes/ADATA SC740/Smugmug Backup/Galleries/Costa-Rica-Gallery/Isla-Tortuga/2021-04-01 10.24.01.jpg",
    "gallery_folder": "Costa-Rica-Gallery/Isla-Tortuga",
    "gallery_id": 47,
    "gallery_slug": "isla-tortuga",
    "filename": "2021-04-01 10.24.01.jpg",
    "content_hash": "3d8ad57f8cc97819f05c7731d5e6a79a73345664411d8e6ffa8af183fe7ef5f2",
    "size": 4642484,
    "approved": true,
    "priority": 50,
    "attempt_count": 0,
    "status": "skipped",
    "skip_reason": "duplicate"
  },
  {
    "id": "ext_Isla-Tortuga_89556795402cc176",
    "type": "photo",
    "source_path": "/Volumes/ADATA SC740/Smugmug Backup/Galleries/Costa-Rica-Gallery/Isla-Tortuga/2021-04-01 10.24.24.jpg",
    "gallery_folder": "Costa-Rica-Gallery/Isla-Tortuga",
    "gallery_id": 47,
    "gallery_slug": "isla-tortuga",
    "filename": "2021-04-01 10.24.24.jpg",
    "content_hash": "89556795402cc17634e390d1ad31eef812117ea244f26901f1d23b27e4d1eeab",
    "size": 6635924,
    "approved": true,
    "priority": 50,
    "attempt_count": 0,
    "status": "skipped",
    "skip_reason": "duplicate"
  },
  {
    "id": "ext_Isla-Tortuga_1daad7ed20551e57",
    "type": "photo",
    "source_path": "/Volumes/ADATA SC740/Smugmug Backup/Galleries/Costa-Rica-Gallery/Isla-Tortuga/2023-12-31 09.59.04.jpg",
    "gallery_folder": "Costa-Rica-Gallery/Isla-Tortuga",
    "gallery_id": 47,
    "gallery_slug": "isla-tortuga",
    "filename": "2023-12-31 09.59.04.jpg",
    "content_hash": "1daad7ed20551e57a09cd3a848a6098803f60d4a785957a76c96fda320eee807",
    "size": 3909874,
    "approved": true,
    "priority": 50,
    "attempt_count": 0,
    "status": "skipped",
    "skip_reason": "duplicate"
  },
  {
    "id": "ext_Isla-Tortuga_7fa0b46a48347cf0",
    "type": "photo",
    "source_path": "/Volumes/ADATA SC740/Smugmug Backup/Galleries/Costa-Rica-Gallery/Isla-Tortuga/2023-12-31 09.59.06.jpg",
    "gallery_folder": "Costa-Rica-Gallery/Isla-Tortuga",
    "gallery_id": 47,
    "gallery_slug": "isla-tortuga",
    "filename": "2023-12-31 09.59.06.jpg",
    "content_hash": "7fa0b46a48347cf0f6f991852a92b708dca4ceffbfa10026947eba20577daec0",
    "size": 3808132,
    "approved": true,
    "priority": 50,
    "attempt_count": 0,
    "status": "skipped",
    "skip_reason": "duplicate"
  },
  {
    "id": "ext_Isla-Tortuga_e96fa8fd8e6569a2",
    "type": "photo",
    "source_path": "/Volumes/ADATA SC740/Smugmug Backup/Galleries/Costa-Rica-Gallery/Isla-Tortuga/2023-12-31 09.59.14.jpg",
    "gallery_folder": "Costa-Rica-Gallery/Isla-Tortuga",
    "gallery_id": 47,
    "gallery_slug": "isla-tortuga",
    "filename": "2023-12-31 09.59.14.jpg",
    "content_hash": "e96fa8fd8e6569a29d9b029f3d500f4dd3dd55cbd1c9e9b6d3c8993c9a24482d",
    "size": 4178420,
    "approved": true,
    "priority": 50,
    "attempt_count": 0,
    "status": "skipped",
    "skip_reason": "duplicate"
  },
  {
    "id": "ext_Isla-Tortuga_00b8dfc857c7e887",
    "type": "photo",
    "source_path": "/Volumes/ADATA SC740/Smugmug Backup/Galleries/Costa-Rica-Gallery/Isla-Tortuga/2023-12-31 09.59.41.jpg",
    "gallery_folder": "Costa-Rica-Gallery/Isla-Tortuga",
    "gallery_id": 47,
    "gallery_slug": "isla-tortuga",
    "filename": "2023-12-31 09.59.41.jpg",
    "content_hash": "00b8dfc857c7e887321b2654d65b8755e406a7496cc8079be429067b84b18198",
    "size": 4194966,
    "approved": true,
    "priority": 50,
    "attempt_count": 0,
    "status": "skipped",
    "skip_reason": "duplicate"
  },
  {
    "id": "ext_Isla-Tortuga_45e8cb0e795aa14b",
    "type": "photo",
    "source_path": "/Volumes/ADATA SC740/Smugmug Backup/Galleries/Costa-Rica-Gallery/Isla-Tortuga/2023-12-31 10.00.29.jpg",
    "gallery_folder": "Costa-Rica-Gallery/Isla-Tortuga",
    "gallery_id": 47,
    "gallery_slug": "isla-tortuga",
    "filename": "2023-12-31 10.00.29.jpg",
    "content_hash": "45e8cb0e795aa14b0a69ad05fc817af4e654b315b14aea5192a54c969a313574",
    "size": 3904221,
    "approved": true,
    "priority": 50,
    "attempt_count": 0,
    "status": "skipped",
    "skip_reason": "duplicate"
  },
  {
    "id": "ext_Isla-Tortuga_c0b151fca9af7fac",
    "type": "photo",
    "source_path": "/Volumes/ADATA SC740/Smugmug Backup/Galleries/Costa-Rica-Gallery/Isla-Tortuga/2023-12-31 10.00.31.jpg",
    "gallery_folder": "Costa-Rica-Gallery/Isla-Tortuga",
    "gallery_id": 47,
    "gallery_slug": "isla-tortuga",
    "filename": "2023-12-31 10.00.31.jpg",
    "content_hash": "c0b151fca9af7fac90f2082b74febbc9872175a8d287bf003640fc10b342e688",
    "size": 3903621,
    "approved": true,
    "priority": 50,
    "attempt_count": 0,
    "status": "skipped",
    "skip_reason": "duplicate"
  },
  {
    "id": "ext_Isla-Tortuga_136797dc9d72573f",
    "type": "photo",
    "source_path": "/Volumes/ADATA SC740/Smugmug Backup/Galleries/Costa-Rica-Gallery/Isla-Tortuga/CL0A1015.JPG",
    "gallery_folder": "Costa-Rica-Gallery/Isla-Tortuga",
    "gallery_id": 47,
    "gallery_slug": "isla-tortuga",
    "filename": "CL0A1015.JPG",
    "content_hash": "136797dc9d72573f6ff027aeaf90ba01399de655bcc4eec954086d8e8f6dbc3a",
    "size": 2474597,
    "approved": true,
    "priority": 50,
    "attempt_count": 0,
    "status": "skipped",
    "skip_reason": "duplicate"
  },
  {
    "id": "ext_Isla-Tortuga_422ff25e349b78a0",
    "type": "photo",
    "source_path": "/Volumes/ADATA SC740/Smugmug Backup/Galleries/Costa-Rica-Gallery/Isla-Tortuga/CL0A1982.jpg",
    "gallery_folder": "Costa-Rica-Gallery/Isla-Tortuga",
    "gallery_id": 47,
    "gallery_slug": "isla-tortuga",
    "filename": "CL0A1982.jpg",
    "content_hash": "422ff25e349b78a079b384f14f3fc48a83956c415f4bc91e8afa0b1be78561d2",
    "size": 4930060,
    "approved": true,
    "priority": 50,
    "attempt_count": 0,
    "status": "skipped",
    "skip_reason": "duplicate"
  },
  {
    "id": "ext_Isla-Tortuga_1f5dafbe0aea0232",
    "type": "photo",
    "source_path": "/Volumes/ADATA SC740/Smugmug Backup/Galleries/Costa-Rica-Gallery/Isla-Tortuga/CL0A1996.jpg",
    "gallery_folder": "Costa-Rica-Gallery/Isla-Tortuga",
    "gallery_id": 47,
    "gallery_slug": "isla-tortuga",
    "filename": "CL0A1996.jpg",
    "content_hash": "1f5dafbe0aea023278dafadcde8d777b794a4f5ba42ecbd3bf8b6a934a8e74f3",
    "size": 6150015,
    "approved": true,
    "priority": 50,
    "attempt_count": 0,
    "status": "skipped",
    "skip_reason": "duplicate"
  },
  {
    "id": "ext_Isla-Tortuga_12f084c43c45a6c5",
    "type": "photo",
    "source_path": "/Volumes/ADATA SC740/Smugmug Backup/Galleries/Costa-Rica-Gallery/Isla-Tortuga/CL0A2000.jpg",
    "gallery_folder": "Costa-Rica-Gallery/Isla-Tortuga",
    "gallery_id": 47,
    "gallery_slug": "isla-tortuga",
    "filename": "CL0A2000.jpg",
    "content_hash": "12f084c43c45a6c5a27e3aa8aec04a2fa5a5fac4022b86096f9118d9588e237e",
    "size": 5408432,
    "approved": true,
    "priority": 50,
    "attempt_count": 0,
    "status": "skipped",
    "skip_reason": "duplicate"
  },
  {
    "id": "ext_Isla-Tortuga_07a1b9102d2201b7",
    "type": "photo",
    "source_path": "/Volumes/ADATA SC740/Smugmug Backup/Galleries/Costa-Rica-Gallery/Isla-Tortuga/CL0A2034.jpg",
    "gallery_folder": "Costa-Rica-Gallery/Isla-Tortuga",
    "gallery_id": 47,
    "gallery_slug": "isla-tortuga",
    "filename": "CL0A2034.jpg",
    "content_hash": "07a1b9102d2201b7abd078af07030dc1db6070bc6e5b0aec5bded8be22944b2b",
    "size": 3214779,
    "approved": true,
    "priority": 50,
    "attempt_count": 0,
    "status": "skipped",
    "skip_reason": "duplicate"
  },
  {
    "id": "ext_Isla-Tortuga_aaf84ddc8363b5fa",
    "type": "photo",
    "source_path": "/Volumes/ADATA SC740/Smugmug Backup/Galleries/Costa-Rica-Gallery/Isla-Tortuga/CL0A2060.jpg",
    "gallery_folder": "Costa-Rica-Gallery/Isla-Tortuga",
    "gallery_id": 47,
    "gallery_slug": "isla-tortuga",
    "filename": "CL0A2060.jpg",
    "content_hash": "aaf84ddc8363b5fa7831ee36c6e1a0fd941b8e82de77e59cb8294bd62215056c",
    "size": 4028838,
    "approved": true,
    "priority": 50,
    "attempt_count": 0,
    "status": "skipped",
    "skip_reason": "duplicate"
  },
  {
    "id": "ext_Isla-Tortuga_8905f4c4bfff94e8",
    "type": "photo",
    "source_path": "/Volumes/ADATA SC740/Smugmug Backup/Galleries/Costa-Rica-Gallery/Isla-Tortuga/CL0A2072.jpg",
    "gallery_folder": "Costa-Rica-Gallery/Isla-Tortuga",
    "gallery_id": 47,
    "gallery_slug": "isla-tortuga",
    "filename": "CL0A2072.jpg",
    "content_hash": "8905f4c4bfff94e8695325809c98bcb5315a5f373e9949959475ce0d6bc0664e",
    "size": 3943387,
    "approved": true,
    "priority": 50,
    "attempt_count": 0,
    "status": "skipped",
    "skip_reason": "duplicate"
  },
  {
    "id": "ext_Isla-Tortuga_1f27652b167b881e",
    "type": "photo",
    "source_path": "/Volumes/ADATA SC740/Smugmug Backup/Galleries/Costa-Rica-Gallery/Isla-Tortuga/CL0A2082.jpg",
    "gallery_folder": "Costa-Rica-Gallery/Isla-Tortuga",
    "gallery_id": 47,
    "gallery_slug": "isla-tortuga",
    "filename": "CL0A2082.jpg",
    "content_hash": "1f27652b167b881ef5992c89e6ca85d818dccf042199a3c3f0978075d98cdd40",
    "size": 5288091,
    "approved": true,
    "priority": 50,
    "attempt_count": 0,
    "status": "skipped",
    "skip_reason": "duplicate"
  },
  {
    "id": "ext_Isla-Tortuga_444a586ff0e6f69a",
    "type": "photo",
    "source_path": "/Volumes/ADATA SC740/Smugmug Backup/Galleries/Costa-Rica-Gallery/Isla-Tortuga/CL0A2085.jpg",
    "gallery_folder": "Costa-Rica-Gallery/Isla-Tortuga",
    "gallery_id": 47,
    "gallery_slug": "isla-tortuga",
    "filename": "CL0A2085.jpg",
    "content_hash": "444a586ff0e6f69a4f0c079046fdd50c529c61097873b8c7fd3f42b9fbc58f4c",
    "size": 5363161,
    "approved": true,
    "priority": 50,
    "attempt_count": 0,
    "status": "skipped",
    "skip_reason": "duplicate"
  },
  {
    "id": "ext_Isla-Tortuga_161dcf6f70568888",
    "type": "photo",
    "source_path": "/Volumes/ADATA SC740/Smugmug Backup/Galleries/Costa-Rica-Gallery/Isla-Tortuga/CL0A2106.jpg",
    "gallery_folder": "Costa-Rica-Gallery/Isla-Tortuga",
    "gallery_id": 47,
    "gallery_slug": "isla-tortuga",
    "filename": "CL0A2106.jpg",
    "content_hash": "161dcf6f70568888c0f5b6c91fb30760b80f40d50a4140093ada5aa263ffdf3b",
    "size": 3628461,
    "approved": true,
    "priority": 50,
    "attempt_count": 0,
    "status": "skipped",
    "skip_reason": "duplicate"
  },
  {
    "id": "ext_Isla-Tortuga_65b1a22b063391f6",
    "type": "photo",
    "source_path": "/Volumes/ADATA SC740/Smugmug Backup/Galleries/Costa-Rica-Gallery/Isla-Tortuga/CL0A7357.JPG",
    "gallery_folder": "Costa-Rica-Gallery/Isla-Tortuga",
    "gallery_id": 47,
    "gallery_slug": "isla-tortuga",
    "filename": "CL0A7357.JPG",
    "content_hash": "65b1a22b063391f65fe50a50bbcb70bb5a85ccc90b0c61a1e6c87850671b4d04",
    "size": 918433,
    "approved": true,
    "priority": 50,
    "attempt_count": 0,
    "status": "skipped",
    "skip_reason": "duplicate"
  },
  {
    "id": "ext_Isla-Tortuga_f49a3dc50d9e2ea4",
    "type": "photo",
    "source_path": "/Volumes/ADATA SC740/Smugmug Backup/Galleries/Costa-Rica-Gallery/Isla-Tortuga/CL0A7366.JPG",
    "gallery_folder": "Costa-Rica-Gallery/Isla-Tortuga",
    "gallery_id": 47,
    "gallery_slug": "isla-tortuga",
    "filename": "CL0A7366.JPG",
    "content_hash": "f49a3dc50d9e2ea42abfd0b30fa8afda96e89cb1a75c73dc4099441b16617148",
    "size": 1544543,
    "approved": true,
    "priority": 50,
    "attempt_count": 0,
    "status": "skipped",
    "skip_reason": "duplicate"
  },
  {
    "id": "ext_Santa-Teresa-Malpais_dba1e9e834c4a78c",
    "type": "photo",
    "source_path": "/Volumes/ADATA SC740/Smugmug Backup/Galleries/Costa-Rica-Gallery/Santa-Teresa-Malpais/2018-08-03 11.20.55-3.jpg",
    "gallery_folder": "Costa-Rica-Gallery/Santa-Teresa-Malpais",
    "gallery_id": 91,
    "gallery_slug": "santa-teresa-malpais",
    "filename": "2018-08-03 11.20.55-3.jpg",
    "content_hash": "dba1e9e834c4a78c09e315e2526885c3f6a937cfd74d32888f257729730cbfa4",
    "size": 7197472,
    "approved": true,
    "priority": 50,
    "attempt_count": 0,
    "status": "skipped",
    "skip_reason": "duplicate"
  },
  {
    "id": "ext_Santa-Teresa-Malpais_e04ac5aae1b66838",
    "type": "photo",
    "source_path": "/Volumes/ADATA SC740/Smugmug Backup/Galleries/Costa-Rica-Gallery/Santa-Teresa-Malpais/2018-08-03 12.48.37.jpg",
    "gallery_folder": "Costa-Rica-Gallery/Santa-Teresa-Malpais",
    "gallery_id": 91,
    "gallery_slug": "santa-teresa-malpais",
    "filename": "2018-08-03 12.48.37.jpg",
    "content_hash": "e04ac5aae1b668385ff79141d7ce24dcc7150f8f9e719b8c47a9303b0d9e2d2b",
    "size": 6673190,
    "approved": true,
    "priority": 50,
    "attempt_count": 0,
    "status": "skipped",
    "skip_reason": "duplicate"
  },
  {
    "id": "ext_Santa-Teresa-Malpais_a64b1ec0028eb201",
    "type": "photo",
    "source_path": "/Volumes/ADATA SC740/Smugmug Backup/Galleries/Costa-Rica-Gallery/Santa-Teresa-Malpais/2018-08-03 12.49.13.jpg",
    "gallery_folder": "Costa-Rica-Gallery/Santa-Teresa-Malpais",
    "gallery_id": 91,
    "gallery_slug": "santa-teresa-malpais",
    "filename": "2018-08-03 12.49.13.jpg",
    "content_hash": "a64b1ec0028eb2011a6a024fc07bd50f052aa6f33f63b16d588aeda08415968d",
    "size": 47751670,
    "approved": true,
    "priority": 50,
    "attempt_count": 0,
    "status": "skipped",
    "skip_reason": "duplicate"
  },
  {
    "id": "ext_Santa-Teresa-Malpais_efab5a7b01532a8a",
    "type": "photo",
    "source_path": "/Volumes/ADATA SC740/Smugmug Backup/Galleries/Costa-Rica-Gallery/Santa-Teresa-Malpais/2021-03-25 11.10.47.jpg",
    "gallery_folder": "Costa-Rica-Gallery/Santa-Teresa-Malpais",
    "gallery_id": 91,
    "gallery_slug": "santa-teresa-malpais",
    "filename": "2021-03-25 11.10.47.jpg",
    "content_hash": "efab5a7b01532a8aba94e5ba8e9ba505eea2d1752b642e01102dad50b1c9430b",
    "size": 7070680,
    "approved": true,
    "priority": 50,
    "attempt_count": 0,
    "status": "skipped",
    "skip_reason": "duplicate"
  },
  {
    "id": "ext_Santa-Teresa-Malpais_573f937b615b8e8c",
    "type": "photo",
    "source_path": "/Volumes/ADATA SC740/Smugmug Backup/Galleries/Costa-Rica-Gallery/Santa-Teresa-Malpais/2021-03-25 11.11.22.jpg",
    "gallery_folder": "Costa-Rica-Gallery/Santa-Teresa-Malpais",
    "gallery_id": 91,
    "gallery_slug": "santa-teresa-malpais",
    "filename": "2021-03-25 11.11.22.jpg",
    "content_hash": "573f937b615b8e8c06ecf3f5b499ab6c952da5c64c67c31669d32dc8440f715a",
    "size": 7186710,
    "approved": true,
    "priority": 50,
    "attempt_count": 0,
    "status": "skipped",
    "skip_reason": "duplicate"
  },
  {
    "id": "ext_Santa-Teresa-Malpais_a0759cab93c9d204",
    "type": "photo",
    "source_path": "/Volumes/ADATA SC740/Smugmug Backup/Galleries/Costa-Rica-Gallery/Santa-Teresa-Malpais/2021-03-25 17.39.30.jpg",
    "gallery_folder": "Costa-Rica-Gallery/Santa-Teresa-Malpais",
    "gallery_id": 91,
    "gallery_slug": "santa-teresa-malpais",
    "filename": "2021-03-25 17.39.30.jpg",
    "content_hash": "a0759cab93c9d2048a3aa246dfcc2e36afd34b8204c341601166d92231c92112",
    "size": 6051424,
    "approved": true,
    "priority": 50,
    "attempt_count": 0,
    "status": "skipped",
    "skip_reason": "duplicate"
  },
  {
    "id": "ext_Santa-Teresa-Malpais_291d758d13cd15bd",
    "type": "photo",
    "source_path": "/Volumes/ADATA SC740/Smugmug Backup/Galleries/Costa-Rica-Gallery/Santa-Teresa-Malpais/2021-03-25 18.14.51.jpg",
    "gallery_folder": "Costa-Rica-Gallery/Santa-Teresa-Malpais",
    "gallery_id": 91,
    "gallery_slug": "santa-teresa-malpais",
    "filename": "2021-03-25 18.14.51.jpg",
    "content_hash": "291d758d13cd15bd2e1a217e26bbf946f37accf82ac2fb739b0d577e45cbd7c1",
    "size": 5831539,
    "approved": true,
    "priority": 50,
    "attempt_count": 0,
    "status": "skipped",
    "skip_reason": "duplicate"
  },
  {
    "id": "ext_Santa-Teresa-Malpais_1578933192e6ff71",
    "type": "photo",
    "source_path": "/Volumes/ADATA SC740/Smugmug Backup/Galleries/Costa-Rica-Gallery/Santa-Teresa-Malpais/2021-03-28 13.36.40.jpg",
    "gallery_folder": "Costa-Rica-Gallery/Santa-Teresa-Malpais",
    "gallery_id": 91,
    "gallery_slug": "santa-teresa-malpais",
    "filename": "2021-03-28 13.36.40.jpg",
    "content_hash": "1578933192e6ff71b6861382299ddbfdbc75f7f8a6e37ded85caa5b8cb67b0be",
    "size": 7333684,
    "approved": true,
    "priority": 50,
    "attempt_count": 0,
    "status": "skipped",
    "skip_reason": "duplicate"
  },
  {
    "id": "ext_Santa-Teresa-Malpais_37763e6b818cabd8",
    "type": "photo",
    "source_path": "/Volumes/ADATA SC740/Smugmug Backup/Galleries/Costa-Rica-Gallery/Santa-Teresa-Malpais/2021-03-29 12.05.17.jpg",
    "gallery_folder": "Costa-Rica-Gallery/Santa-Teresa-Malpais",
    "gallery_id": 91,
    "gallery_slug": "santa-teresa-malpais",
    "filename": "2021-03-29 12.05.17.jpg",
    "content_hash": "37763e6b818cabd8e9acef25bd8a33d72d59376d8221c182db07208f5bdd7bf1",
    "size": 6827851,
    "approved": true,
    "priority": 50,
    "attempt_count": 0,
    "status": "skipped",
    "skip_reason": "duplicate"
  },
  {
    "id": "ext_Santa-Teresa-Malpais_cd8656d1913d3fde",
    "type": "photo",
    "source_path": "/Volumes/ADATA SC740/Smugmug Backup/Galleries/Costa-Rica-Gallery/Santa-Teresa-Malpais/2021-03-30 11.20.41.jpg",
    "gallery_folder": "Costa-Rica-Gallery/Santa-Teresa-Malpais",
    "gallery_id": 91,
    "gallery_slug": "santa-teresa-malpais",
    "filename": "2021-03-30 11.20.41.jpg",
    "content_hash": "cd8656d1913d3fdef4db9aaa9d63a2d46f08d1b7886bf770220d7e10b6571e35",
    "size": 2095370,
    "approved": true,
    "priority": 50,
    "attempt_count": 0,
    "status": "skipped",
    "skip_reason": "duplicate"
  },
  {
    "id": "ext_Santa-Teresa-Malpais_eebf9542ef19e83a",
    "type": "photo",
    "source_path": "/Volumes/ADATA SC740/Smugmug Backup/Galleries/Costa-Rica-Gallery/Santa-Teresa-Malpais/2021-03-30 14.30.46.jpg",
    "gallery_folder": "Costa-Rica-Gallery/Santa-Teresa-Malpais",
    "gallery_id": 91,
    "gallery_slug": "santa-teresa-malpais",
    "filename": "2021-03-30 14.30.46.jpg",
    "content_hash": "eebf9542ef19e83ac30e8246f6a2394a65968514b71383b2dc9519691a49d308",
    "size": 8235509,
    "approved": true,
    "priority": 50,
    "attempt_count": 0,
    "status": "skipped",
    "skip_reason": "duplicate"
  },
  {
    "id": "ext_Santa-Teresa-Malpais_5fb0ae296aaf260a",
    "type": "photo",
    "source_path": "/Volumes/ADATA SC740/Smugmug Backup/Galleries/Costa-Rica-Gallery/Santa-Teresa-Malpais/2021-05-17 06.37.37.jpg",
    "gallery_folder": "Costa-Rica-Gallery/Santa-Teresa-Malpais",
    "gallery_id": 91,
    "gallery_slug": "santa-teresa-malpais",
    "filename": "2021-05-17 06.37.37.jpg",
    "content_hash": "5fb0ae296aaf260a088be104cce8c87fae91d23a471415c7f8b3683564b614d3",
    "size": 5276943,
    "approved": true,
    "priority": 50,
    "attempt_count": 0,
    "status": "skipped",
    "skip_reason": "duplicate"
  },
  {
    "id": "ext_Santa-Teresa-Malpais_4368f46937a31666",
    "type": "photo",
    "source_path": "/Volumes/ADATA SC740/Smugmug Backup/Galleries/Costa-Rica-Gallery/Santa-Teresa-Malpais/2023-12-30 12.40.49.jpg",
    "gallery_folder": "Costa-Rica-Gallery/Santa-Teresa-Malpais",
    "gallery_id": 91,
    "gallery_slug": "santa-teresa-malpais",
    "filename": "2023-12-30 12.40.49.jpg",
    "content_hash": "4368f46937a31666d3b17e52be32b0561ee46d4d012292a47d594c3a2ce2c212",
    "size": 5678231,
    "approved": true,
    "priority": 50,
    "attempt_count": 0,
    "status": "skipped",
    "skip_reason": "duplicate"
  },
  {
    "id": "ext_Santa-Teresa-Malpais_48795b783fcb44d7",
    "type": "photo",
    "source_path": "/Volumes/ADATA SC740/Smugmug Backup/Galleries/Costa-Rica-Gallery/Santa-Teresa-Malpais/2023-12-30 13.22.04.jpg",
    "gallery_folder": "Costa-Rica-Gallery/Santa-Teresa-Malpais",
    "gallery_id": 91,
    "gallery_slug": "santa-teresa-malpais",
    "filename": "2023-12-30 13.22.04.jpg",
    "content_hash": "48795b783fcb44d7a272a225d9e612275998eee27d728bdc33f12f2355bb3ac8",
    "size": 6665086,
    "approved": true,
    "priority": 50,
    "attempt_count": 0,
    "status": "skipped",
    "skip_reason": "duplicate"
  },
  {
    "id": "ext_Santa-Teresa-Malpais_e71d8c7c6651895f",
    "type": "photo",
    "source_path": "/Volumes/ADATA SC740/Smugmug Backup/Galleries/Costa-Rica-Gallery/Santa-Teresa-Malpais/2023-12-30 13.22.06.jpg",
    "gallery_folder": "Costa-Rica-Gallery/Santa-Teresa-Malpais",
    "gallery_id": 91,
    "gallery_slug": "santa-teresa-malpais",
    "filename": "2023-12-30 13.22.06.jpg",
    "content_hash": "e71d8c7c6651895fbfd0ae7dd5c7d6282508b3221e17d8d4cee80c22067762d1",
    "size": 6347092,
    "approved": true,
    "priority": 50,
    "attempt_count": 0,
    "status": "skipped",
    "skip_reason": "duplicate"
  },
  {
    "id": "ext_Santa-Teresa-Malpais_63e2437bc646d1f7",
    "type": "photo",
    "source_path": "/Volumes/ADATA SC740/Smugmug Backup/Galleries/Costa-Rica-Gallery/Santa-Teresa-Malpais/2023-12-30 13.27.26.jpg",
    "gallery_folder": "Costa-Rica-Gallery/Santa-Teresa-Malpais",
    "gallery_id": 91,
    "gallery_slug": "santa-teresa-malpais",
    "filename": "2023-12-30 13.27.26.jpg",
    "content_hash": "63e2437bc646d1f7c7cdb1f5aab03cbc3fbb10bb14e01af7bf847c6e7de09e6e",
    "size": 4989781,
    "approved": true,
    "priority": 50,
    "attempt_count": 0,
    "status": "skipped",
    "skip_reason": "duplicate"
  },
  {
    "id": "ext_Santa-Teresa-Malpais_9eb56e6206747a9b",
    "type": "photo",
    "source_path": "/Volumes/ADATA SC740/Smugmug Backup/Galleries/Costa-Rica-Gallery/Santa-Teresa-Malpais/2023-12-30 13.29.21.jpg",
    "gallery_folder": "Costa-Rica-Gallery/Santa-Teresa-Malpais",
    "gallery_id": 91,
    "gallery_slug": "santa-teresa-malpais",
    "filename": "2023-12-30 13.29.21.jpg",
    "content_hash": "9eb56e6206747a9b94273f6951d60bc3752ab5761c582ad4f75a8d97e7e4a612",
    "size": 5636246,
    "approved": true,
    "priority": 50,
    "attempt_count": 0,
    "status": "skipped",
    "skip_reason": "duplicate"
  },
  {
    "id": "ext_Santa-Teresa-Malpais_0fc3050d118e13c9",
    "type": "photo",
    "source_path": "/Volumes/ADATA SC740/Smugmug Backup/Galleries/Costa-Rica-Gallery/Santa-Teresa-Malpais/2023-12-30 13.29.25.jpg",
    "gallery_folder": "Costa-Rica-Gallery/Santa-Teresa-Malpais",
    "gallery_id": 91,
    "gallery_slug": "santa-teresa-malpais",
    "filename": "2023-12-30 13.29.25.jpg",
    "content_hash": "0fc3050d118e13c96401af3f13072da351e75e120e56769e6a73570e69770868",
    "size": 5435446,
    "approved": true,
    "priority": 50,
    "attempt_count": 0,
    "status": "skipped",
    "skip_reason": "duplicate"
  },
  {
    "id": "ext_Santa-Teresa-Malpais_35cfa93fbebae7a4",
    "type": "photo",
    "source_path": "/Volumes/ADATA SC740/Smugmug Backup/Galleries/Costa-Rica-Gallery/Santa-Teresa-Malpais/2023-12-30 13.29.29.jpg",
    "gallery_folder": "Costa-Rica-Gallery/Santa-Teresa-Malpais",
    "gallery_id": 91,
    "gallery_slug": "santa-teresa-malpais",
    "filename": "2023-12-30 13.29.29.jpg",
    "content_hash": "35cfa93fbebae7a4b212175f6e19758798cd6fd87867474ec259a633615fd49f",
    "size": 5515649,
    "approved": true,
    "priority": 50,
    "attempt_count": 0,
    "status": "skipped",
    "skip_reason": "duplicate"
  },
  {
    "id": "ext_Santa-Teresa-Malpais_d042510d061119f9",
    "type": "photo",
    "source_path": "/Volumes/ADATA SC740/Smugmug Backup/Galleries/Costa-Rica-Gallery/Santa-Teresa-Malpais/2023-12-30 15.57.04.jpg",
    "gallery_folder": "Costa-Rica-Gallery/Santa-Teresa-Malpais",
    "gallery_id": 91,
    "gallery_slug": "santa-teresa-malpais",
    "filename": "2023-12-30 15.57.04.jpg",
    "content_hash": "d042510d061119f9e71046cd63a7855cd70415a8a562ed27b83115e133cc2d0d",
    "size": 4877618,
    "approved": true,
    "priority": 50,
    "attempt_count": 0,
    "status": "skipped",
    "skip_reason": "duplicate"
  },
  {
    "id": "ext_Golfo-de-Nicoya_5f84ae21ae656e3b",
    "type": "photo",
    "source_path": "/Volumes/ADATA SC740/Smugmug Backup/Galleries/Costa-Rica-Gallery/Golfo-de-Nicoya/CL0A0710.jpg",
    "gallery_folder": "Costa-Rica-Gallery/Golfo-de-Nicoya",
    "gallery_id": 39,
    "gallery_slug": "golfo-de-nicoya",
    "filename": "CL0A0710.jpg",
    "content_hash": "5f84ae21ae656e3bb808c5ed78a6a5bb05a74535356c52e37dd3fef1e491e99e",
    "size": 3120696,
    "approved": true,
    "priority": 50,
    "attempt_count": 0,
    "status": "skipped",
    "skip_reason": "duplicate"
  },
  {
    "id": "ext_Golfo-de-Nicoya_d0158937b4252f60",
    "type": "photo",
    "source_path": "/Volumes/ADATA SC740/Smugmug Backup/Galleries/Costa-Rica-Gallery/Golfo-de-Nicoya/CL0A0774.jpg",
    "gallery_folder": "Costa-Rica-Gallery/Golfo-de-Nicoya",
    "gallery_id": 39,
    "gallery_slug": "golfo-de-nicoya",
    "filename": "CL0A0774.jpg",
    "content_hash": "d0158937b4252f6068d2bd2b4ea8453b015fc0b58204f51fadecd463eac9dab8",
    "size": 4476903,
    "approved": true,
    "priority": 50,
    "attempt_count": 0,
    "status": "skipped",
    "skip_reason": "duplicate"
  },
  {
    "id": "ext_Golfo-de-Nicoya_17878b93117768c9",
    "type": "photo",
    "source_path": "/Volumes/ADATA SC740/Smugmug Backup/Galleries/Costa-Rica-Gallery/Golfo-de-Nicoya/CL0A0780.jpg",
    "gallery_folder": "Costa-Rica-Gallery/Golfo-de-Nicoya",
    "gallery_id": 39,
    "gallery_slug": "golfo-de-nicoya",
    "filename": "CL0A0780.jpg",
    "content_hash": "17878b93117768c966d82477cf6c0261912f3457ae13ad8b8eaf76849bd217cb",
    "size": 5188793,
    "approved": true,
    "priority": 50,
    "attempt_count": 0,
    "status": "skipped",
    "skip_reason": "duplicate"
  },
  {
    "id": "ext_Golfo-de-Nicoya_1669327b9561a9b4",
    "type": "photo",
    "source_path": "/Volumes/ADATA SC740/Smugmug Backup/Galleries/Costa-Rica-Gallery/Golfo-de-Nicoya/CL0A3760.JPG",
    "gallery_folder": "Costa-Rica-Gallery/Golfo-de-Nicoya",
    "gallery_id": 39,
    "gallery_slug": "golfo-de-nicoya",
    "filename": "CL0A3760.JPG",
    "content_hash": "1669327b9561a9b425c7b79474801ed46cee9b5ab7fa40686aa0d4001862695b",
    "size": 3856931,
    "approved": true,
    "priority": 50,
    "attempt_count": 0,
    "status": "skipped",
    "skip_reason": "duplicate"
  },
  {
    "id": "ext_Golfo-de-Nicoya_4afba92cbb8485ef",
    "type": "photo",
    "source_path": "/Volumes/ADATA SC740/Smugmug Backup/Galleries/Costa-Rica-Gallery/Golfo-de-Nicoya/CL0A4577.jpg",
    "gallery_folder": "Costa-Rica-Gallery/Golfo-de-Nicoya",
    "gallery_id": 39,
    "gallery_slug": "golfo-de-nicoya",
    "filename": "CL0A4577.jpg",
    "content_hash": "4afba92cbb8485efc60521e2ac437074f6c58e064377c97edc8907efda4fc955",
    "size": 2534843,
    "approved": true,
    "priority": 50,
    "attempt_count": 0,
    "status": "skipped",
    "skip_reason": "duplicate"
  },
  {
    "id": "ext_Golfo-de-Nicoya_79ce35f8742b3017",
    "type": "photo",
    "source_path": "/Volumes/ADATA SC740/Smugmug Backup/Galleries/Costa-Rica-Gallery/Golfo-de-Nicoya/CL0A5820.jpg",
    "gallery_folder": "Costa-Rica-Gallery/Golfo-de-Nicoya",
    "gallery_id": 39,
    "gallery_slug": "golfo-de-nicoya",
    "filename": "CL0A5820.jpg",
    "content_hash": "79ce35f8742b30177eba112525c20f317eabbfb1544b9aa99452dce5b615ac84",
    "size": 2418863,
    "approved": true,
    "priority": 50,
    "attempt_count": 0,
    "status": "skipped",
    "skip_reason": "duplicate"
  },
  {
    "id": "ext_Golfo-de-Nicoya_56161445ce066a27",
    "type": "photo",
    "source_path": "/Volumes/ADATA SC740/Smugmug Backup/Galleries/Costa-Rica-Gallery/Golfo-de-Nicoya/CL0A5824.jpg",
    "gallery_folder": "Costa-Rica-Gallery/Golfo-de-Nicoya",
    "gallery_id": 39,
    "gallery_slug": "golfo-de-nicoya",
    "filename": "CL0A5824.jpg",
    "content_hash": "56161445ce066a27e7773bf5ac9876c6c90686355ee24beac652e3e82b52ca2c",
    "size": 5170226,
    "approved": true,
    "priority": 50,
    "attempt_count": 0,
    "status": "skipped",
    "skip_reason": "duplicate"
  },
  {
    "id": "ext_Golfo-de-Nicoya_6a6c09aea7865b86",
    "type": "photo",
    "source_path": "/Volumes/ADATA SC740/Smugmug Backup/Galleries/Costa-Rica-Gallery/Golfo-de-Nicoya/CL0A5883.jpg",
    "gallery_folder": "Costa-Rica-Gallery/Golfo-de-Nicoya",
    "gallery_id": 39,
    "gallery_slug": "golfo-de-nicoya",
    "filename": "CL0A5883.jpg",
    "content_hash": "6a6c09aea7865b86eb973e14f0065c2a918618322de1ac09a7bbb342c76eb8be",
    "size": 3532888,
    "approved": true,
    "priority": 50,
    "attempt_count": 0,
    "status": "skipped",
    "skip_reason": "duplicate"
  },
  {
    "id": "ext_Golfo-de-Nicoya_594205a1b87f33a3",
    "type": "photo",
    "source_path": "/Volumes/ADATA SC740/Smugmug Backup/Galleries/Costa-Rica-Gallery/Golfo-de-Nicoya/DJI_0027.jpg",
    "gallery_folder": "Costa-Rica-Gallery/Golfo-de-Nicoya",
    "gallery_id": 39,
    "gallery_slug": "golfo-de-nicoya",
    "filename": "DJI_0027.jpg",
    "content_hash": "594205a1b87f33a34e39523164a15eed64b727c5269121cac45ab238ce564c33",
    "size": 12510553,
    "approved": true,
    "priority": 50,
    "attempt_count": 0,
    "status": "skipped",
    "skip_reason": "duplicate"
  },
  {
    "id": "ext_Golfo-de-Nicoya_9c382d3332f83d08",
    "type": "photo",
    "source_path": "/Volumes/ADATA SC740/Smugmug Backup/Galleries/Costa-Rica-Gallery/Golfo-de-Nicoya/DJI_0045.jpg",
    "gallery_folder": "Costa-Rica-Gallery/Golfo-de-Nicoya",
    "gallery_id": 39,
    "gallery_slug": "golfo-de-nicoya",
    "filename": "DJI_0045.jpg",
    "content_hash": "9c382d3332f83d08257df0f0453b9bc0752996505582bec97e57983bd8201be3",
    "size": 11707806,
    "approved": true,
    "priority": 50,
    "attempt_count": 0,
    "status": "skipped",
    "skip_reason": "duplicate"
  },
  {
    "id": "ext_Golfo-de-Nicoya_195bb168f056acda",
    "type": "photo",
    "source_path": "/Volumes/ADATA SC740/Smugmug Backup/Galleries/Costa-Rica-Gallery/Golfo-de-Nicoya/DJI_0050.jpg",
    "gallery_folder": "Costa-Rica-Gallery/Golfo-de-Nicoya",
    "gallery_id": 39,
    "gallery_slug": "golfo-de-nicoya",
    "filename": "DJI_0050.jpg",
    "content_hash": "195bb168f056acdacc400475c564dc9d3a03049bda999246d99f8c71a6d92c04",
    "size": 11998625,
    "approved": true,
    "priority": 50,
    "attempt_count": 0,
    "status": "skipped",
    "skip_reason": "duplicate"
  },
  {
    "id": "ext_Golfo-de-Nicoya_f123ddc7083272c8",
    "type": "photo",
    "source_path": "/Volumes/ADATA SC740/Smugmug Backup/Galleries/Costa-Rica-Gallery/Golfo-de-Nicoya/DJI_0054.jpg",
    "gallery_folder": "Costa-Rica-Gallery/Golfo-de-Nicoya",
    "gallery_id": 39,
    "gallery_slug": "golfo-de-nicoya",
    "filename": "DJI_0054.jpg",
    "content_hash": "f123ddc7083272c83d2697c080d9d3428f4415cccfac8210e483c1fb2e25a5bf",
    "size": 12887455,
    "approved": true,
    "priority": 50,
    "attempt_count": 0,
    "status": "skipped",
    "skip_reason": "duplicate"
  },
  {
    "id": "ext_Golfo-de-Nicoya_7e73bde6e3d9de6c",
    "type": "photo",
    "source_path": "/Volumes/ADATA SC740/Smugmug Backup/Galleries/Costa-Rica-Gallery/Golfo-de-Nicoya/DJI_0055.jpg",
    "gallery_folder": "Costa-Rica-Gallery/Golfo-de-Nicoya",
    "gallery_id": 39,
    "gallery_slug": "golfo-de-nicoya",
    "filename": "DJI_0055.jpg",
    "content_hash": "7e73bde6e3d9de6caeee1b1347815cac96088276b560ea1a590bf1c3b98efb49",
    "size": 12387741,
    "approved": true,
    "priority": 50,
    "attempt_count": 0,
    "status": "skipped",
    "skip_reason": "duplicate"
  },
  {
    "id": "ext_Golfo-de-Nicoya_a4bfe333dc4d9c34",
    "type": "photo",
    "source_path": "/Volumes/ADATA SC740/Smugmug Backup/Galleries/Costa-Rica-Gallery/Golfo-de-Nicoya/DJI_0060.jpg",
    "gallery_folder": "Costa-Rica-Gallery/Golfo-de-Nicoya",
    "gallery_id": 39,
    "gallery_slug": "golfo-de-nicoya",
    "filename": "DJI_0060.jpg",
    "content_hash": "a4bfe333dc4d9c34e1a9823e7052c846d5c4b197ae8d2b53c7513e64c597621d",
    "size": 13522335,
    "approved": true,
    "priority": 50,
    "attempt_count": 0,
    "status": "skipped",
    "skip_reason": "duplicate"
  },
  {
    "id": "ext_Golfo-de-Nicoya_2672fa4b77fadd19",
    "type": "photo",
    "source_path": "/Volumes/ADATA SC740/Smugmug Backup/Galleries/Costa-Rica-Gallery/Golfo-de-Nicoya/DJI_0062.jpg",
    "gallery_folder": "Costa-Rica-Gallery/Golfo-de-Nicoya",
    "gallery_id": 39,
    "gallery_slug": "golfo-de-nicoya",
    "filename": "DJI_0062.jpg",
    "content_hash": "2672fa4b77fadd19cf4d370c3a7d16f376270c157137e7dd8e470f9601159909",
    "size": 34792862,
    "approved": true,
    "priority": 50,
    "attempt_count": 0,
    "status": "skipped",
    "skip_reason": "duplicate"
  },
  {
    "id": "ext_Golfo-de-Nicoya_da71453ca9d1d7f5",
    "type": "photo",
    "source_path": "/Volumes/ADATA SC740/Smugmug Backup/Galleries/Costa-Rica-Gallery/Golfo-de-Nicoya/DJI_0063.jpg",
    "gallery_folder": "Costa-Rica-Gallery/Golfo-de-Nicoya",
    "gallery_id": 39,
    "gallery_slug": "golfo-de-nicoya",
    "filename": "DJI_0063.jpg",
    "content_hash": "da71453ca9d1d7f518b133ca3433a9c0c602d14d082c37366e24903985d9ee76",
    "size": 31536543,
    "approved": true,
    "priority": 50,
    "attempt_count": 0,
    "status": "skipped",
    "skip_reason": "duplicate"
  },
  {
    "id": "ext_Golfo-de-Nicoya_44d9fdde44e3ca83",
    "type": "photo",
    "source_path": "/Volumes/ADATA SC740/Smugmug Backup/Galleries/Costa-Rica-Gallery/Golfo-de-Nicoya/DJI_0080.jpg",
    "gallery_folder": "Costa-Rica-Gallery/Golfo-de-Nicoya",
    "gallery_id": 39,
    "gallery_slug": "golfo-de-nicoya",
    "filename": "DJI_0080.jpg",
    "content_hash": "44d9fdde44e3ca836f2de184430c7074ba2839cb8fd80eea9084a708ee259948",
    "size": 10864031,
    "approved": true,
    "priority": 50,
    "attempt_count": 0,
    "status": "skipped",
    "skip_reason": "duplicate"
  },
  {
    "id": "ext_Golfo-de-Nicoya_867ad1e3b24f2e91",
    "type": "photo",
    "source_path": "/Volumes/ADATA SC740/Smugmug Backup/Galleries/Costa-Rica-Gallery/Golfo-de-Nicoya/DJI_0081.jpg",
    "gallery_folder": "Costa-Rica-Gallery/Golfo-de-Nicoya",
    "gallery_id": 39,
    "gallery_slug": "golfo-de-nicoya",
    "filename": "DJI_0081.jpg",
    "content_hash": "867ad1e3b24f2e9159783e69440c66a2f1d25ac85323d37b4e003ac170787d96",
    "size": 11900321,
    "approved": true,
    "priority": 50,
    "attempt_count": 0,
    "status": "skipped",
    "skip_reason": "duplicate"
  },
  {
    "id": "ext_Golfo-de-Nicoya_43cda5848014fb83",
    "type": "photo",
    "source_path": "/Volumes/ADATA SC740/Smugmug Backup/Galleries/Costa-Rica-Gallery/Golfo-de-Nicoya/DJI_0084.jpg",
    "gallery_folder": "Costa-Rica-Gallery/Golfo-de-Nicoya",
    "gallery_id": 39,
    "gallery_slug": "golfo-de-nicoya",
    "filename": "DJI_0084.jpg",
    "content_hash": "43cda5848014fb83acbf85fba1743ed3e18a31b4cf616f1b4979d8f52eb1a0f3",
    "size": 11593119,
    "approved": true,
    "priority": 50,
    "attempt_count": 0,
    "status": "skipped",
    "skip_reason": "duplicate"
  },
  {
    "id": "ext_Golfo-de-Nicoya_c8225d3d6d02f180",
    "type": "photo",
    "source_path": "/Volumes/ADATA SC740/Smugmug Backup/Galleries/Costa-Rica-Gallery/Golfo-de-Nicoya/DJI_0085.jpg",
    "gallery_folder": "Costa-Rica-Gallery/Golfo-de-Nicoya",
    "gallery_id": 39,
    "gallery_slug": "golfo-de-nicoya",
    "filename": "DJI_0085.jpg",
    "content_hash": "c8225d3d6d02f180c3d0a00e1fad52be96286990b554654de38ed094934dd1a7",
    "size": 11744671,
    "approved": true,
    "priority": 50,
    "attempt_count": 0,
    "status": "skipped",
    "skip_reason": "duplicate"
  },
  {
    "id": "ext_Peninsula-de-Osa_db920f6d40ddebae",
    "type": "photo",
    "source_path": "/Volumes/ADATA SC740/Smugmug Backup/Galleries/Costa-Rica-Gallery/Peninsula-de-Osa/2020-09-12 12.49.08.jpg",
    "gallery_folder": "Costa-Rica-Gallery/Peninsula-de-Osa",
    "gallery_id": 67,
    "gallery_slug": "peninsula-de-osa",
    "filename": "2020-09-12 12.49.08.jpg",
    "content_hash": "db920f6d40ddebae8678c1c64bc52c3500642af27feafcf4dc532a531f651d56",
    "size": 5102407,
    "approved": true,
    "priority": 50,
    "attempt_count": 0,
    "status": "completed",
    "skip_reason": null,
    "db_id": 23272
  },
  {
    "id": "ext_Peninsula-de-Osa_132c2b86663923c6",
    "type": "photo",
    "source_path": "/Volumes/ADATA SC740/Smugmug Backup/Galleries/Costa-Rica-Gallery/Peninsula-de-Osa/2020-09-13 07.24.17-1.jpg",
    "gallery_folder": "Costa-Rica-Gallery/Peninsula-de-Osa",
    "gallery_id": 67,
    "gallery_slug": "peninsula-de-osa",
    "filename": "2020-09-13 07.24.17-1.jpg",
    "content_hash": "132c2b86663923c6f4cd2add36d4daf3fc9fa5bfbce4de312a8c89a77a3d90ee",
    "size": 5715065,
    "approved": true,
    "priority": 50,
    "attempt_count": 0,
    "status": "completed",
    "skip_reason": null,
    "db_id": 23273
  },
  {
    "id": "ext_Peninsula-de-Osa_c5a1852cdb305edb",
    "type": "photo",
    "source_path": "/Volumes/ADATA SC740/Smugmug Backup/Galleries/Costa-Rica-Gallery/Peninsula-de-Osa/2020-09-13 07.25.30.jpg",
    "gallery_folder": "Costa-Rica-Gallery/Peninsula-de-Osa",
    "gallery_id": 67,
    "gallery_slug": "peninsula-de-osa",
    "filename": "2020-09-13 07.25.30.jpg",
    "content_hash": "c5a1852cdb305edbc081d0fc188ebec6149f5e8f911f12775e49e56184a8ef04",
    "size": 6265096,
    "approved": true,
    "priority": 50,
    "attempt_count": 0,
    "status": "completed",
    "skip_reason": null,
    "db_id": 23274
  },
  {
    "id": "ext_Peninsula-de-Osa_fd013ceaa0772ef8",
    "type": "photo",
    "source_path": "/Volumes/ADATA SC740/Smugmug Backup/Galleries/Costa-Rica-Gallery/Peninsula-de-Osa/2020-09-13 07.27.26.jpg",
    "gallery_folder": "Costa-Rica-Gallery/Peninsula-de-Osa",
    "gallery_id": 67,
    "gallery_slug": "peninsula-de-osa",
    "filename": "2020-09-13 07.27.26.jpg",
    "content_hash": "fd013ceaa0772ef8f9f934879e5582d8aab4e39483a3061142ea4e525d8e1573",
    "size": 5557807,
    "approved": true,
    "priority": 50,
    "attempt_count": 0,
    "status": "completed",
    "skip_reason": null,
    "db_id": 23275
  },
  {
    "id": "ext_Peninsula-de-Osa_712a7aad6155e941",
    "type": "photo",
    "source_path": "/Volumes/ADATA SC740/Smugmug Backup/Galleries/Costa-Rica-Gallery/Peninsula-de-Osa/2020-09-13 07.27.37-1.jpg",
    "gallery_folder": "Costa-Rica-Gallery/Peninsula-de-Osa",
    "gallery_id": 67,
    "gallery_slug": "peninsula-de-osa",
    "filename": "2020-09-13 07.27.37-1.jpg",
    "content_hash": "712a7aad6155e941e63b0c76a0a2e38064a96c93e06b7ec7842b8f7ff65105f9",
    "size": 4708169,
    "approved": true,
    "priority": 50,
    "attempt_count": 0,
    "status": "completed",
    "skip_reason": null,
    "db_id": 23276
  },
  {
    "id": "ext_Peninsula-de-Osa_0235d8f4c403a4ff",
    "type": "photo",
    "source_path": "/Volumes/ADATA SC740/Smugmug Backup/Galleries/Costa-Rica-Gallery/Peninsula-de-Osa/2020-09-14 08.41.44.jpg",
    "gallery_folder": "Costa-Rica-Gallery/Peninsula-de-Osa",
    "gallery_id": 67,
    "gallery_slug": "peninsula-de-osa",
    "filename": "2020-09-14 08.41.44.jpg",
    "content_hash": "0235d8f4c403a4ffefc8dd29a56431a70cccfba1b58bcafa368f01aaea5dea7f",
    "size": 4178042,
    "approved": true,
    "priority": 50,
    "attempt_count": 0,
    "status": "completed",
    "skip_reason": null,
    "db_id": 23277
  },
  {
    "id": "ext_Peninsula-de-Osa_e675b17ae318d1e7",
    "type": "photo",
    "source_path": "/Volumes/ADATA SC740/Smugmug Backup/Galleries/Costa-Rica-Gallery/Peninsula-de-Osa/2020-09-14 10.56.16.jpg",
    "gallery_folder": "Costa-Rica-Gallery/Peninsula-de-Osa",
    "gallery_id": 67,
    "gallery_slug": "peninsula-de-osa",
    "filename": "2020-09-14 10.56.16.jpg",
    "content_hash": "e675b17ae318d1e72a73683969d25e54eac5d82e144a0e0aca65541738fb48cf",
    "size": 3790939,
    "approved": true,
    "priority": 50,
    "attempt_count": 0,
    "status": "completed",
    "skip_reason": null,
    "db_id": 23278
  },
  {
    "id": "ext_Peninsula-de-Osa_193b3a4e95da088a",
    "type": "photo",
    "source_path": "/Volumes/ADATA SC740/Smugmug Backup/Galleries/Costa-Rica-Gallery/Peninsula-de-Osa/2020-09-14 11.00.05.jpg",
    "gallery_folder": "Costa-Rica-Gallery/Peninsula-de-Osa",
    "gallery_id": 67,
    "gallery_slug": "peninsula-de-osa",
    "filename": "2020-09-14 11.00.05.jpg",
    "content_hash": "193b3a4e95da088a76d6d820b49e45b19843c95254d721c763f0958c57864d2b",
    "size": 4963530,
    "approved": true,
    "priority": 50,
    "attempt_count": 0,
    "status": "completed",
    "skip_reason": null,
    "db_id": 23279
  },
  {
    "id": "ext_Peninsula-de-Osa_5f65be1278febac7",
    "type": "photo",
    "source_path": "/Volumes/ADATA SC740/Smugmug Backup/Galleries/Costa-Rica-Gallery/Peninsula-de-Osa/2020-09-14 12.02.01.jpg",
    "gallery_folder": "Costa-Rica-Gallery/Peninsula-de-Osa",
    "gallery_id": 67,
    "gallery_slug": "peninsula-de-osa",
    "filename": "2020-09-14 12.02.01.jpg",
    "content_hash": "5f65be1278febac7b9c0d17dfd04b4b30b3965e9ed73bebf654962af4235ff28",
    "size": 6532018,
    "approved": true,
    "priority": 50,
    "attempt_count": 0,
    "status": "completed",
    "skip_reason": null,
    "db_id": 23280
  },
  {
    "id": "ext_Peninsula-de-Osa_f2d8a459df8f0456",
    "type": "photo",
    "source_path": "/Volumes/ADATA SC740/Smugmug Backup/Galleries/Costa-Rica-Gallery/Peninsula-de-Osa/DJI_0585.jpg",
    "gallery_folder": "Costa-Rica-Gallery/Peninsula-de-Osa",
    "gallery_id": 67,
    "gallery_slug": "peninsula-de-osa",
    "filename": "DJI_0585.jpg",
    "content_hash": "f2d8a459df8f0456f8afcab0b55feea758f666995d062ffd43c9f6aabd959eb4",
    "size": 5989301,
    "approved": true,
    "priority": 50,
    "attempt_count": 0,
    "status": "completed",
    "skip_reason": null,
    "db_id": 23281
  },
  {
    "id": "ext_Peninsula-de-Osa_229dc3d6dad7d454",
    "type": "photo",
    "source_path": "/Volumes/ADATA SC740/Smugmug Backup/Galleries/Costa-Rica-Gallery/Peninsula-de-Osa/DJI_0625-3.jpg",
    "gallery_folder": "Costa-Rica-Gallery/Peninsula-de-Osa",
    "gallery_id": 67,
    "gallery_slug": "peninsula-de-osa",
    "filename": "DJI_0625-3.jpg",
    "content_hash": "229dc3d6dad7d4540f14c4bd751655b2fdfa158638bc99c0d420db3f3145657e",
    "size": 9945247,
    "approved": true,
    "priority": 50,
    "attempt_count": 0,
    "status": "completed",
    "skip_reason": null,
    "db_id": 23282
  },
  {
    "id": "ext_Peninsula-de-Osa_cfc07a3e198e7116",
    "type": "photo",
    "source_path": "/Volumes/ADATA SC740/Smugmug Backup/Galleries/Costa-Rica-Gallery/Peninsula-de-Osa/DJI_0626.JPG",
    "gallery_folder": "Costa-Rica-Gallery/Peninsula-de-Osa",
    "gallery_id": 67,
    "gallery_slug": "peninsula-de-osa",
    "filename": "DJI_0626.JPG",
    "content_hash": "cfc07a3e198e711692123ebfd7dde3420f5191778f27018d05f32ea676664e9a",
    "size": 6753918,
    "approved": true,
    "priority": 50,
    "attempt_count": 0,
    "status": "completed",
    "skip_reason": null,
    "db_id": 23283
  },
  {
    "id": "ext_Peninsula-de-Osa_e4e5befbee07d160",
    "type": "photo",
    "source_path": "/Volumes/ADATA SC740/Smugmug Backup/Galleries/Costa-Rica-Gallery/Peninsula-de-Osa/DJI_0628.jpg",
    "gallery_folder": "Costa-Rica-Gallery/Peninsula-de-Osa",
    "gallery_id": 67,
    "gallery_slug": "peninsula-de-osa",
    "filename": "DJI_0628.jpg",
    "content_hash": "e4e5befbee07d160fa7e300134b34ac0e0b59b2b10b27db2ca6e102e318bc29a",
    "size": 19300300,
    "approved": true,
    "priority": 50,
    "attempt_count": 0,
    "status": "completed",
    "skip_reason": null,
    "db_id": 23284
  },
  {
    "id": "ext_Peninsula-de-Osa_d2c57dd7356d7751",
    "type": "photo",
    "source_path": "/Volumes/ADATA SC740/Smugmug Backup/Galleries/Costa-Rica-Gallery/Peninsula-de-Osa/DJI_0629.JPG",
    "gallery_folder": "Costa-Rica-Gallery/Peninsula-de-Osa",
    "gallery_id": 67,
    "gallery_slug": "peninsula-de-osa",
    "filename": "DJI_0629.JPG",
    "content_hash": "d2c57dd7356d7751be8583670a757b078543aa64d690e4030756cd4316a0f82e",
    "size": 4787436,
    "approved": true,
    "priority": 50,
    "attempt_count": 0,
    "status": "completed",
    "skip_reason": null,
    "db_id": 23285
  },
  {
    "id": "ext_Peninsula-de-Osa_3d75b76758a24437",
    "type": "photo",
    "source_path": "/Volumes/ADATA SC740/Smugmug Backup/Galleries/Costa-Rica-Gallery/Peninsula-de-Osa/DJI_0630-2.jpg",
    "gallery_folder": "Costa-Rica-Gallery/Peninsula-de-Osa",
    "gallery_id": 67,
    "gallery_slug": "peninsula-de-osa",
    "filename": "DJI_0630-2.jpg",
    "content_hash": "3d75b76758a2443720b09ab53a0e180df884a81ae04991505f6ab13f195a067c",
    "size": 8576103,
    "approved": true,
    "priority": 50,
    "attempt_count": 0,
    "status": "completed",
    "skip_reason": null,
    "db_id": 23286
  },
  {
    "id": "ext_Peninsula-de-Osa_4a1e5172064d9225",
    "type": "photo",
    "source_path": "/Volumes/ADATA SC740/Smugmug Backup/Galleries/Costa-Rica-Gallery/Peninsula-de-Osa/DJI_0631.JPG",
    "gallery_folder": "Costa-Rica-Gallery/Peninsula-de-Osa",
    "gallery_id": 67,
    "gallery_slug": "peninsula-de-osa",
    "filename": "DJI_0631.JPG",
    "content_hash": "4a1e5172064d922501a5fc4a86f9c9679ceb669cead13a1c78e7dc9b479c6f30",
    "size": 5867868,
    "approved": true,
    "priority": 50,
    "attempt_count": 0,
    "status": "completed",
    "skip_reason": null,
    "db_id": 23287
  },
  {
    "id": "ext_Peninsula-de-Osa_ba24fd3e84a00072",
    "type": "photo",
    "source_path": "/Volumes/ADATA SC740/Smugmug Backup/Galleries/Costa-Rica-Gallery/Peninsula-de-Osa/DJI_0638.JPG",
    "gallery_folder": "Costa-Rica-Gallery/Peninsula-de-Osa",
    "gallery_id": 67,
    "gallery_slug": "peninsula-de-osa",
    "filename": "DJI_0638.JPG",
    "content_hash": "ba24fd3e84a00072c867b8ee5c2953ed8ea769eefc532aff069b20dc47f18ca7",
    "size": 5741523,
    "approved": true,
    "priority": 50,
    "attempt_count": 0,
    "status": "completed",
    "skip_reason": null,
    "db_id": 23288
  },
  {
    "id": "ext_Peninsula-de-Osa_f681672dfbe5b8bb",
    "type": "photo",
    "source_path": "/Volumes/ADATA SC740/Smugmug Backup/Galleries/Costa-Rica-Gallery/Peninsula-de-Osa/DJI_0640.JPG",
    "gallery_folder": "Costa-Rica-Gallery/Peninsula-de-Osa",
    "gallery_id": 67,
    "gallery_slug": "peninsula-de-osa",
    "filename": "DJI_0640.JPG",
    "content_hash": "f681672dfbe5b8bb060c3472514e772de232f769e6a87544bcdac423c5f5fa09",
    "size": 5613611,
    "approved": true,
    "priority": 50,
    "attempt_count": 0,
    "status": "completed",
    "skip_reason": null,
    "db_id": 23289
  },
  {
    "id": "ext_Peninsula-de-Osa_aaa9660ca40bfa7c",
    "type": "photo",
    "source_path": "/Volumes/ADATA SC740/Smugmug Backup/Galleries/Costa-Rica-Gallery/Peninsula-de-Osa/DJI_0642.JPG",
    "gallery_folder": "Costa-Rica-Gallery/Peninsula-de-Osa",
    "gallery_id": 67,
    "gallery_slug": "peninsula-de-osa",
    "filename": "DJI_0642.JPG",
    "content_hash": "aaa9660ca40bfa7c89f7db2f818273fce89f8738e475bc5b8c01da8504e71be1",
    "size": 8287862,
    "approved": true,
    "priority": 50,
    "attempt_count": 0,
    "status": "completed",
    "skip_reason": null,
    "db_id": 23290
  },
  {
    "id": "ext_Peninsula-de-Osa_61df78c682effa85",
    "type": "photo",
    "source_path": "/Volumes/ADATA SC740/Smugmug Backup/Galleries/Costa-Rica-Gallery/Peninsula-de-Osa/DJI_0646.JPG",
    "gallery_folder": "Costa-Rica-Gallery/Peninsula-de-Osa",
    "gallery_id": 67,
    "gallery_slug": "peninsula-de-osa",
    "filename": "DJI_0646.JPG",
    "content_hash": "61df78c682effa859ea7f677aee462ba37536b1e5d8d80985dbd76043b948648",
    "size": 3819018,
    "approved": true,
    "priority": 50,
    "attempt_count": 0,
    "status": "completed",
    "skip_reason": null,
    "db_id": 23291
  }
]